quote_chart.py
quote_chart-0.1.3.dist-info/LICENSE.txt
quote_chart-0.1.3.dist-info/METADATA
quote_chart-0.1.3.dist-info/WHEEL
quote_chart-0.1.3.dist-info/top_level.txt
quote_chart-0.1.3.dist-info/RECORD
