Metadata-Version: 2.1
Name: quote_chart
Version: 0.1.3
Summary: Customized dash/plotly chart for price candles.
Home-page: https://github.com/barsv/quote_chart
Author: Stan
Author-email: barsvquotechart@gmail.com
Classifier: Programming Language :: Python :: 3
Classifier: License :: OSI Approved :: MIT License
Classifier: Operating System :: OS Independent
Requires-Python: >=3.6
License-File: LICENSE.txt
Requires-Dist: dash
Requires-Dist: numpy <2.0.0
